{"id":"92fbcc13585c40b7a9b2f3b2a00c332f","title":"에러 타입 테스트 모바일","asset":[{"assetId":"cdedc6adb9e641f78bcd05dca3d2884f","assetType":"I","mimeType":"image/png","originFileName":"애초에 핑크.png","w":"927","h":"165","duration":"","link":false},{"assetId":"5e45432ce20d4961868186902de3469a","assetType":"I","mimeType":"image/png","originFileName":"미안해.png","w":"929","h":"164","duration":"","link":false},{"assetId":"dc8f1fd56583498fb68bf765f9aa5bd1","assetType":"I","mimeType":"image/png","originFileName":"첫화면_start.png","w":"506","h":"58","duration":"","link":false},{"assetId":"4728bef4225c45e28b900518b3be8aa4","assetType":"I","mimeType":"image/png","originFileName":"백업된 파일이.png","w":"929","h":"164","duration":"","link":false},{"assetId":"1a34141427b641d5a86016393a3aee80","assetType":"I","mimeType":"image/png","originFileName":"일단 충격받고 .png","w":"929","h":"164","duration":"","link":false},{"assetId":"00a17fda42064fa8b8730694a0b58072","assetType":"I","mimeType":"image/png","originFileName":"다음엔.png","w":"928","h":"164","duration":"","link":false},{"assetId":"ec58572a27174edb9924c248d421d141","assetType":"I","mimeType":"image/png","originFileName":"처음부터.png","w":"928","h":"164","duration":"","link":false},{"assetId":"66935a82e79349a7b903493f80fd029c","assetType":"I","mimeType":"image/png","originFileName":"KakaoTalk_20241006_112125342.png","w":"888","h":"45","duration":"","link":false},{"assetId":"e887aa9db1ac4fa98507f2fe09230556","assetType":"I","mimeType":"image/png","originFileName":"여러가지 방안을.png","w":"929","h":"164","duration":"","link":false},{"assetId":"6f290fce48904f80aba894fcf118176b","assetType":"I","mimeType":"image/png","originFileName":"하 난 도대체 핑크.png","w":"927","h":"165","duration":"","link":false},{"assetId":"f3df113bfd84456a974441e6149076b5","assetType":"I","mimeType":"image/png","originFileName":"결과화면_온화.png","w":"1180","h":"2557","duration":"","link":false},{"assetId":"4af93781e3c54416971c07f86bd1e734","assetType":"I","mimeType":"image/png","originFileName":"KakaoTalk_20241030_090202102_01.png","w":"109","h":"109","duration":"","link":false},{"assetId":"eab02dbdea1c480da7adb40ad79ee7fc","assetType":"I","mimeType":"image/png","originFileName":"처음부터 핑크.png","w":"927","h":"165","duration":"","link":false},{"assetId":"87d630d4d5634638888d0edc0533ec7a","assetType":"I","mimeType":"image/png","originFileName":"바로 직원을 부른다.png","w":"929","h":"164","duration":"","link":false},{"assetId":"97ba498968624146993037d179151e70","assetType":"I","mimeType":"image/png","originFileName":"자꾸 실수하는데 핑크.png","w":"927","h":"165","duration":"","link":false},{"assetId":"f2c84b9df50343b9a5d9d4bd60291113","assetType":"I","mimeType":"image/png","originFileName":"자꾸 실수하는데 .png","w":"929","h":"164","duration":"","link":false},{"assetId":"924120323b75487381b909fbe6bd86ab","assetType":"I","mimeType":"image/png","originFileName":"망설이거나 핑크.png","w":"927","h":"165","duration":"","link":false},{"assetId":"0c85b73cdd9b4d8a8314397ea7eca285","assetType":"I","mimeType":"image/png","originFileName":"빠르게 이메일을 핑크png.png","w":"927","h":"181","duration":"","link":false},{"assetId":"bff560cf495b49bf807f1090db418eac","assetType":"I","mimeType":"image/png","originFileName":"미안해 핑크.png","w":"927","h":"165","duration":"","link":false},{"assetId":"1355c4734ccd47108cee7a7c9eadb1f5","assetType":"I","mimeType":"image/png","originFileName":"일단 충격받고 핑크png.png","w":"927","h":"165","duration":"","link":false},{"assetId":"da849360e32c47d7bfa9e209faf5be68","assetType":"I","mimeType":"image/png","originFileName":"주문서를 다시 확인해본다.png","w":"929","h":"164","duration":"","link":false},{"assetId":"089277544cce47269d42656544193523","assetType":"I","mimeType":"image/png","originFileName":"결과화면_신중.png","w":"1180","h":"2557","duration":"","link":false},{"assetId":"96990af46f3b48d89cc8b83172cc40fb","assetType":"I","mimeType":"image/png","originFileName":"KakaoTalk_20241028_172916922_01.png","w":"1180","h":"2557","duration":"","link":false},{"assetId":"65fb1f1a4d0146e7bc3e5a8a02d767cb","assetType":"I","mimeType":"image/png","originFileName":"바로 직원을 부른다 핑크.png","w":"928","h":"165","duration":"","link":false},{"assetId":"ca3deaea3d44436fb5797cfd3513f330","assetType":"I","mimeType":"image/png","originFileName":"실수는 하지만 핑크.png","w":"927","h":"165","duration":"","link":false},{"assetId":"c55a7eb3a1d641f482180a81eecbbb06","assetType":"I","mimeType":"image/png","originFileName":"왜 늦었는지.png","w":"929","h":"164","duration":"","link":false},{"assetId":"1b6b3aeb698c46a185da24af3ec07d66","assetType":"I","mimeType":"image/png","originFileName":"망설이거나.png","w":"929","h":"164","duration":"","link":false},{"assetId":"1f741a43f2ff43429efaf4ccd4d51a38","assetType":"I","mimeType":"image/png","originFileName":"KakaoTalk_20241028_172916922_03.png","w":"1179","h":"2557","duration":"","link":false},{"assetId":"be5904d052054370b1357b041b5d92d5","assetType":"I","mimeType":"image/png","originFileName":"대지 28.png","w":"498","h":"140","duration":"","link":false},{"assetId":"f64e48e43ca64ea6ab1e07ec191707ed","assetType":"I","mimeType":"image/png","originFileName":"빠르게 이메일을.png","w":"929","h":"188","duration":"","link":false},{"assetId":"95daf2ef9cf848098141eca98e7d8e0b","assetType":"I","mimeType":"image/png","originFileName":"부족하지만 핑크.png","w":"927","h":"165","duration":"","link":false},{"assetId":"b90f725dad53406f90101b24af40726e","assetType":"I","mimeType":"image/png","originFileName":"결과 화면_유연.png","w":"1180","h":"2557","duration":"","link":false},{"assetId":"8a092790bce14f9ba749932db3662e73","assetType":"I","mimeType":"image/png","originFileName":"백업된 파일이 있는지 핑크.png","w":"927","h":"165","duration":"","link":false},{"assetId":"cd5c9ff050c44587ab4af09d70fa558d","assetType":"I","mimeType":"image/png","originFileName":"KakaoTalk_20241028_172638724.png","w":"1179","h":"2557","duration":"","link":false},{"assetId":"7d43105becb24d6ba44e5c9a9b30e6fc","assetType":"I","mimeType":"image/png","originFileName":"괜찮아핑크.png","w":"927","h":"165","duration":"","link":false},{"assetId":"1525b5ab8d3343ef91ce3f5968267631","assetType":"I","mimeType":"image/png","originFileName":"왜 늦었는지 핑크.png","w":"927","h":"165","duration":"","link":false},{"assetId":"b5d17e5daad64fd98929a95a419806cc","assetType":"I","mimeType":"image/png","originFileName":"나 자신을 받아들인다 핑크.png","w":"927","h":"165","duration":"","link":false},{"assetId":"595bb595d8b944db9cc4dc791d05ba98","assetType":"I","mimeType":"image/png","originFileName":"하 난 도대체.png","w":"929","h":"164","duration":"","link":false},{"assetId":"a137ec5052f14e70b0997a082119cd8c","assetType":"I","mimeType":"image/png","originFileName":"여러가지 방안을 핑크.png","w":"927","h":"165","duration":"","link":false},{"assetId":"10411c9e703d4880a67367aa20668ecc","assetType":"I","mimeType":"image/png","originFileName":"결과화면_명료.png","w":"1180","h":"2557","duration":"","link":false},{"assetId":"225cf4a0bfff468a925c454d38972065","assetType":"I","mimeType":"image/png","originFileName":"KakaoTalk_20241006_112125342_02.png","w":"1134","h":"441","duration":"","link":false},{"assetId":"bbd7a20da83347d18b4b2296c6a4d1c1","assetType":"I","mimeType":"image/png","originFileName":"주문서를 다시 확인해본다 ㅍ핑크.png","w":"927","h":"165","duration":"","link":false},{"assetId":"539640e380414223a13b13af73a4ff8c","assetType":"I","mimeType":"image/png","originFileName":"실수는 하지만.png","w":"929","h":"164","duration":"","link":false},{"assetId":"067580755189435e94efc3b80055dde1","assetType":"I","mimeType":"image/png","originFileName":"애초에 .png","w":"928","h":"164","duration":"","link":false},{"assetId":"90f6be5e750a4393bfab361d2fffef59","assetType":"I","mimeType":"image/png","originFileName":"괜찮아 .png","w":"929","h":"164","duration":"","link":false},{"assetId":"14e9761fb346460db6769a7cd3e0b5fe","assetType":"I","mimeType":"image/png","originFileName":"다음엔 핑크.png","w":"927","h":"165","duration":"","link":false},{"assetId":"12361c0b00a245c992532377ecde12b1","assetType":"I","mimeType":"image/png","originFileName":"KakaoTalk_20241028_172916922_02.png","w":"1180","h":"2557","duration":"","link":false},{"assetId":"722cd2c481284c3f90b4fe9c2ca8d9b7","assetType":"I","mimeType":"image/png","originFileName":"부족하지만 .png","w":"928","h":"164","duration":"","link":false},{"assetId":"42f24aeaaa31486db1026816938e29f9","assetType":"I","mimeType":"image/png","originFileName":"나 자신을 받아들인다.png","w":"928","h":"164","duration":"","link":false},{"assetId":"cbf17b0442e245d7ae1921b730cc1822","assetType":"A","mimeType":"audio/mpeg","originFileName":"click.mp3","w":"0","h":"0","duration":"","link":false},{"assetId":"c0e300ac6f55487ab3dcf6350b874c45","assetType":"A","mimeType":"audio/mpeg","originFileName":"loading.mp3","w":"0","h":"0","duration":"","link":false}]}